MANIFEST.in
README.md
setup.py
sentinews/__init__.py
sentinews.egg-info/PKG-INFO
sentinews.egg-info/SOURCES.txt
sentinews.egg-info/dependency_links.txt
sentinews.egg-info/requires.txt
sentinews.egg-info/top_level.txt
sentinews/docs/model/category
sentinews/docs/model/default_best.h5
sentinews/docs/model/params
sentinews/docs/model/vocabulary_inv
sentinews/scripts/__init__.py
sentinews/scripts/sentiment_train.py
sentinews/utils/__init__.py
sentinews/utils/assemble.py
sentinews/utils/config.yaml
sentinews/utils/dataHelper.py