Metadata-Version: 1.1
Name: sentinews
Version: 0.4.1
Summary: sentiment classifier for news trained by LSTM.
Home-page: https://github.com/KillersDeath/the_machine
Author: Liujie zhang
Author-email: liujiezhangbupt@gmail.com
License: MIT
Keywords: sentiment,LSTM
Platform: UNKNOWN
Classifier: Development Status :: 3 - Alpha
Classifier: Intended Audience :: Developers
Classifier: Programming Language :: Python
Classifier: Programming Language :: Python :: 2.7
